{"expireTime":9007201004202456000,"key":"transformer-remark-markdown-html-ast-a1cd5a675ee9425a42b31e476d10f7a0-gatsby-remark-external-linksgatsby-remark-imagesgatsby-remark-code-titlesgatsby-remark-prismjs-","val":{"type":"root","children":[{"type":"element","tagName":"ul","properties":{},"children":[{"type":"text","value":"\n"},{"type":"element","tagName":"li","properties":{},"children":[{"type":"text","value":"Designed and prototyped new features for a non-profit Chinese-language career platform","position":{"start":{"line":2,"column":3,"offset":3},"end":{"line":2,"column":89,"offset":89}}}],"position":{"start":{"line":2,"column":1,"offset":1},"end":{"line":2,"column":89,"offset":89}}},{"type":"text","value":"\n"},{"type":"element","tagName":"li","properties":{},"children":[{"type":"text","value":"Created user flows and interactive mockups in Figma","position":{"start":{"line":3,"column":3,"offset":92},"end":{"line":3,"column":54,"offset":143}}}],"position":{"start":{"line":3,"column":1,"offset":90},"end":{"line":3,"column":54,"offset":143}}},{"type":"text","value":"\n"},{"type":"element","tagName":"li","properties":{},"children":[{"type":"text","value":"Collaborated closely with engineers to ensure accurate implementation of UI components","position":{"start":{"line":4,"column":3,"offset":146},"end":{"line":4,"column":89,"offset":232}}}],"position":{"start":{"line":4,"column":1,"offset":144},"end":{"line":4,"column":89,"offset":232}}},{"type":"text","value":"\n"}],"position":{"start":{"line":2,"column":1,"offset":1},"end":{"line":4,"column":89,"offset":232}}}],"position":{"start":{"line":1,"column":1,"offset":0},"end":{"line":5,"column":1,"offset":233}}}}